{
    "tap_size": 12,
    "approximation_l2": 1.593564528367063e-30,
    "delay": {
        "even": 2,
        "odd": 3
    },
    "steps": [
        {
            "type": "predict",
            "shift": 1,
            "coefficients": [
                4.434468298690675
            ]
        },
        {
            "type": "update",
            "shift": -1,
            "coefficients": [
                -0.21459345000300822,
                -0.03698755309328884
            ]
        },
        {
            "type": "predict",
            "shift": 0,
            "coefficients": [
                9.970015612798727,
                -22.123015286620667
            ]
        },
        {
            "type": "update",
            "shift": -1,
            "coefficients": [
                0.03354120921838349,
                -0.0813799050703406
            ]
        },
        {
            "type": "predict",
            "shift": 0,
            "coefficients": [
                11.602828079472708,
                -40.280878559897076
            ]
        },
        {
            "type": "update",
            "shift": -1,
            "coefficients": [
                0.024704622773498667,
                -0.17904902004943432
            ]
        },
        {
            "type": "predict",
            "shift": 0,
            "coefficients": [
                5.584541732942351
            ]
        },
        {
            "type": "scale",
            "shift": 0,
            "coefficients": [
                -0.23224456094617063
            ]
        }
    ]
}